{
	"PAGE_TYPES": [
		{ "value": "home", "label": { "vi": "Trang chủ", "en": "Home" } },
		{ "value": "blog", "label": { "vi": "Blog", "en": "Blog" } },
		{ "value": "blog_category", "label": { "vi": "Danh mục blog", "en": "Blog Category" } },
		{ "value": "contact", "label": { "vi": "Liên hệ", "en": "Contact" } }
	],
	"PAGE_POSITIONS": [
		{ "value": "header", "label": { "vi": "Đầu trang", "en": "Header" } },
		{ "value": "main", "label": { "vi": "Trang chính", "en": "Main" } },
		{ "value": "footer", "label": { "vi": "Cuối trang", "en": "Footer" } },
		{ "value": "top", "label": { "vi": "Trên cùng", "en": "Top" } },
		{ "value": "left", "label": { "vi": "Bên trái", "en": "Left" } },
		{ "value": "bottom", "label": { "vi": "Dưới cùng", "en": "Bottom" } },
		{ "value": "right", "label": { "vi": "Bên phải", "en": "Right" } }
	]
}
